<?xml version="1.0" encoding="UTF-8"?>
<!DOCTYPE yml_catalog SYSTEM "shops.dtd">

<yml_catalog date="2025-07-05 19:07:04">
  <shop>
    <name>TOP ELF BAR</name>
    <company>TOP ELF BAR</company>
    <url>https://lsshop.1b.app</url>
    <platform>OneBox</platform>
    <version>1.0</version>
    <agency>OneBox</agency>
    <agency>OneBox</agency>
    <email>support@crm-onebox.com</email>
    <currencies>
      <currency id="UAH" rate="1.000000" />
    </currencies>
    <categories>
      <category id="5127" parentId="926">Брелоки</category>
    </categories>
    <offers />
  </shop>
</yml_catalog>

